[{    
    "id": -1,    
    "text": "水雨情监测",    
    "state": "open",    
    "children": [{    
        "id": -10,    
        "text": "水情实时数据",
		"children": [{    
			"id": 101,    
			"text": "水情实时数据表"   
		}]
    },{    
        "id": -11,    
        "text": "库水位报表统计",
		"children": [{    
			"id": 111,    
			"text": "时段报表统计"   
		},{    
			"id": 112,    
			"text": "月报表统计"   
		},{    
			"id": 113,    
			"text": "单点年报表统计"   
		}]
    },{    
        "id": -12,    
        "text": "库水位过程线",
		"children": [{    
			"id": 121,    
			"text": "时段过程线"   
		},{    
			"id": 122,    
			"text": "月过程线"   
		},{    
			"id": 123,    
			"text": "单点年过程线"   
		}]
    },{    
        "id": -13,    
        "text": "降雨量报表统计",
		"children": [{    
			"id": 131,    
			"text": "时段报表统计"   
		},{    
			"id": 132,    
			"text": "月报表统计"   
		},{    
			"id": 133,    
			"text": "单点年报表统计"   
		}]
    },{    
        "id": -14,    
        "text": "降雨量过程线",
		"children": [{    
			"id": 141,    
			"text": "时段过程线"   
		},{    
			"id": 142,    
			"text": "月过程线"   
		},{    
			"id": 143,    
			"text": "单点年过程线"   
		}]
    },{    
        "id": -15,    
        "text": "报警信息",
		"children": [{    
			"id": 151,    
			"text": "报警查询"   
		}]
    }]    
},
{    
    "id": -2,    
    "text": "大坝监测",    
    "state": "open",    
    "children": [{    
        "id": -20,    
        "text": "大坝监测",
		"children": [{    
			"id": 201,    
			"text": "大坝数据监测"   
		},{    
			"id": 202,    
			"text": "断面 I"   
		},{    
			"id": 203,    
			"text": "断面 II"   
		},{    
			"id": 204,    
			"text": "断面 III"   
		},{    
			"id": 205,    
			"text": "断面 IV"   
		},{    
			"id": 206,    
			"text": "断面 V"   
		},{    
			"id": 207,    
			"text": "溢洪道"   
		}]
    },{    
        "id": -21,    
        "text": "渗压报表统计",
		"children": [{    
			"id": 211,    
			"text": "时段报表统计"   
		},{    
			"id": 212,    
			"text": "月报表统计"   
		},{    
			"id": 213,    
			"text": "单点年报表统计"   
		}]
    },{    
        "id": -22,    
        "text": "渗压过程线",
		"children": [{    
			"id": 221,    
			"text": "时段过程线"   
		},{    
			"id": 222,    
			"text": "月过程线"   
		},{    
			"id": 223,    
			"text": "单点年过程线"   
		}]
    },{    
        "id": -23,    
        "text": "渗流报表统计",
		"children": [{    
			"id": 231,    
			"text": "时段报表统计"   
		},{    
			"id": 232,    
			"text": "月报表统计"   
		},{    
			"id": 233,    
			"text": "单点年报表统计"   
		}]
    },{    
        "id": -24,    
        "text": "渗流过程线",
		"children": [{    
			"id": 241,    
			"text": "时段过程线"   
		},{    
			"id": 242,    
			"text": "月过程线"   
		},{    
			"id": 243,    
			"text": "单点年过程线"   
		}]
    },{    
        "id": -25,    
        "text": "报警信息",
		"children": [{    
			"id": 251,    
			"text": "报警查询"   
		}]
    }]    
},
{    
    "id": -3,    
    "text": "变形观测",    
    "state": "open",    
    "children": [{    
        "id": -30,    
        "text": "变形观测",
		"children": [{    
			"id": 301,    
			"text": "实时监测"   
		}]
    },{    
        "id": -31,    
        "text": "报表统计",
		"children": [{    
			"id": 311,    
			"text": "时段报表统计"   
		},{    
			"id": 312,    
			"text": "月报表统计"   
		},{    
			"id": 313,    
			"text": "年报表统计"   
		},{    
			"id": 314,    
			"text": "单点年报表统计"   
		}]
    },{    
        "id": -32,    
        "text": "过程线",
		"children": [{    
			"id": 321,    
			"text": "时段过程线"   
		},{    
			"id": 322,    
			"text": "月过程线"   
		},{    
			"id": 323,    
			"text": "年过程线"   
		},{    
			"id": 324,    
			"text": "单点年过程线"   
		}]
    },{    
        "id": -34,    
        "text": "分布图",
		"children": [{    
			"id": 341,    
			"text": "纵断面竖向位移分布图"   
		},{    
			"id": 342,    
			"text": "纵断面水平位移分布图"   
		},{    
			"id": 343,    
			"text": "横断面竖向位移分布图"   
		}]
    },{    
        "id": -33,    
        "text": "报警信息",
		"children": [{    
			"id": 331,    
			"text": "报警查询"   
		}]
    }]    
},
{    
    "id": -4,    
    "text": "闸门监控",    
    "state": "open",    
    "children": [{    
        "id": -40,    
        "text": "闸门监控",
		"children": [{    
			"id": 401,    
			"text": "1#闸门实时监控"   
		},{    
			"id": 402,    
			"text": "2#闸门实时监控"   
		}]
    },{    
        "id": -41,    
        "text": "报表统计",
		"children": [{    
			"id": 411,    
			"text": "报表统计"   
		}]
    },{    
        "id": -42,    
        "text": "报警信息",
		"children": [{    
			"id": 421,    
			"text": "报警查询"   
		}]
    }]    
},
{    
    "id": -5,    
    "text": "洪水预报",    
    "state": "open",    
    "children": [{    
        "id": 50,    
        "text": "洪水预报"
    }]    
},
{    
    "id": -6,    
    "text": "防洪调度",    
    "state": "open",    
    "children": [{    
        "id": 60,    
        "text": "防洪调度"
    }]    
},
{    
    "id": -7,    
    "text": "报警信息",    
    "state": "open",    
    "children": [{    
        "id": -70,    
        "text": "水雨情报警信息",
		"children": [{    
			"id": 701,    
			"text": "报警查询"   
		}]
    },{    
        "id": -71,    
        "text": "大坝安全报警信息",
		"children": [{    
			"id": 711,    
			"text": "报警查询"   
		}]
    },{    
        "id": -72,    
        "text": "变形观测报警信息",
		"children": [{    
			"id": 721,    
			"text": "报警查询"   
		}]
    },{    
        "id": -73,    
        "text": "闸门监控报警信息",
		"children": [{    
			"id": 731,    
			"text": "报警查询"   
		}]
    }]    
},
{    
    "id": -8,    
    "text": "信息平台",    
    "state": "open",    
    "children": [{    
        "id": 80,    
        "text": "微信平台"
    },{    
        "id": 81,    
        "text": "邮件平台"
    },{    
        "id": 82,    
        "text": "APP消息推送平台"
    },{    
        "id": 83,    
        "text": "短信平台"
    }]    
},
{    
    "id": -9,    
    "text": "系统设置",    
    "state": "open",    
    "children": [{    
        "id": 90,    
        "text": "员工管理"
    },{    
        "id": 91,    
        "text": "模块操作管理"
    },{    
        "id": 92,    
        "text": "员工权限管理"
    },{    
        "id": 93,    
        "text": "系统日志"
    }]    
}]

